exec_wrapper/__init__.py
exec_wrapper/_nt_launcher.exe
exec_wrapper/py.typed
exec_wrapper-0.1.0.dist-info/WHEEL
exec_wrapper-0.1.0.dist-info/METADATA
exec_wrapper-0.1.0.dist-info/RECORD
