Metadata-Version: 2.1
Name: exec-wrapper
Version: 0.1.0
Summary: Allows creating executable wrappers for any executable
Author: xppt
Author-email: 21246102+xppt@users.noreply.github.com
Requires-Python: >=3.6,<4.0
Classifier: Programming Language :: Python :: 3
Classifier: Programming Language :: Python :: 3.6
Classifier: Programming Language :: Python :: 3.7
Classifier: Programming Language :: Python :: 3.8
Classifier: Programming Language :: Python :: 3.9
